discord/ext/menus/__init__.py
discord_ext_menus-1.1.dist-info/LICENSE
discord_ext_menus-1.1.dist-info/METADATA
discord_ext_menus-1.1.dist-info/WHEEL
discord_ext_menus-1.1.dist-info/top_level.txt
discord_ext_menus-1.1.dist-info/RECORD
