Metadata-Version: 1.2
Name: discord-ext-menus
Version: 1.1
Summary: An extension module to make reaction based menus with discord.py
Home-page: https://github.com/Rapptz/discord-ext-menus
Author: Rapptz
License: MIT
Platform: UNKNOWN
Requires-Python: >=3.5.3
